genson/__init__.py
genson/generator.py
genson/genson.py
genson-0.1.0.dist-info/DESCRIPTION.rst
genson-0.1.0.dist-info/entry_points.txt
genson-0.1.0.dist-info/METADATA
genson-0.1.0.dist-info/metadata.json
genson-0.1.0.dist-info/RECORD
genson-0.1.0.dist-info/top_level.txt
genson-0.1.0.dist-info/WHEEL
genson-0.1.0.dist-info/zip-safe
