Metadata-Version: 1.1
Name: genson
Version: 0.1.0
Summary: GenSON is a powerful, user-friendly JSON Schema generator.
Home-page: https://github.com/wolverdude/genson/
Author: Jon Wolverton
Author-email: wolverton.jr@gmail.com
License: MIT
Download-URL: https://github.com/wolverdude/GenSON/tarball/v0.1.0
Keywords: json,schema,object,generate,generator,builder,draft 4,validate,validation
Platform: UNKNOWN
Classifier: Development Status :: 4 - Beta
Classifier: Intended Audience :: Developers
Classifier: Natural Language :: English
Classifier: License :: OSI Approved :: MIT License
Classifier: Operating System :: OS Independent
Classifier: Programming Language :: Python
Classifier: Programming Language :: Python :: 2
Classifier: Programming Language :: Python :: 2.7
Classifier: Programming Language :: Python :: 3
Classifier: Programming Language :: Python :: 3.3
Classifier: Topic :: Software Development :: Libraries :: Python Modules
Classifier: Topic :: Utilities
